brushable_widget/__init__.py
brushable_widget/static/widget.css
brushable_widget/static/widget.js
brushable_widget/static/widget_old.js
brushable_widget/static/widget_working.js
brushable_widget-0.1.8.dist-info/METADATA
brushable_widget-0.1.8.dist-info/WHEEL
brushable_widget-0.1.8.dist-info/RECORD
