Metadata-Version: 2.4
Name: brushable_widget
Version: 0.1.8
Requires-Dist: anywidget
Requires-Dist: marimo>=0.11.17
Requires-Dist: svg-py>=1.5.0
